aiomixcloud/__init__.py
aiomixcloud/auth.py
aiomixcloud/constants.py
aiomixcloud/core.py
aiomixcloud/datetime.py
aiomixcloud/decorators.py
aiomixcloud/exceptions.py
aiomixcloud/json.py
aiomixcloud/models.py
aiomixcloud/sync.py
aiomixcloud-1.0.6.dist-info/DESCRIPTION.rst
aiomixcloud-1.0.6.dist-info/LICENSE.txt
aiomixcloud-1.0.6.dist-info/METADATA
aiomixcloud-1.0.6.dist-info/RECORD
aiomixcloud-1.0.6.dist-info/WHEEL
aiomixcloud-1.0.6.dist-info/metadata.json
aiomixcloud-1.0.6.dist-info/top_level.txt
